src/__init__.py
src/azure_client.py
src/bitbucket_client.py
src/google_client.py
src/imports.py
src/jira_client.py
src/leona.py
src/utils.py
leona-1.0.8.dist-info/METADATA
leona-1.0.8.dist-info/WHEEL
leona-1.0.8.dist-info/entry_points.txt
leona-1.0.8.dist-info/top_level.txt
leona-1.0.8.dist-info/RECORD
