Metadata-Version: 2.1
Name: leona
Version: 1.0.8
Summary: CLI for DevOps Integration
Home-page: https://bitbucket.org/hlcn/leona
Author: Juan Guillermo Escalona
Author-email: j.escalona@hlcn.mx
License: UNKNOWN
Platform: UNKNOWN
Requires-Python: >=3.7.6
Requires-Dist: bullet (==2.1.0)
Requires-Dist: click (==7.1.2)
Requires-Dist: jira (==2.0.0)
Requires-Dist: pymsteams (==0.1.12)
Requires-Dist: python-dotenv (==0.13.0)
Requires-Dist: PyYAML (==5.3.1)
Requires-Dist: requests (==2.23.0)
Requires-Dist: questionary (==1.5.2)
Requires-Dist: azurerm (==0.10.0)
Requires-Dist: google-play-scraper (==0.1.2)
